<?xml version="1.0" encoding="utf-8" ?><dwsync><file name="Plakat-Huehner-neu.jpg" server="www.kinderkultur.ch/httpdocs/" local="3535638725" remote="319783739179434988" Dst="-1" /><file name="achdiesehuehnenplakat.jpg" server="www.kinderkultur.ch/httpdocs/" local="3535638725" remote="319783739179434988" Dst="-1" /><file name="huehner2.jpg" server="www.kinderkultur.ch/httpdocs/" local="3535638726" remote="319783739179434988" Dst="-1" /><file name="huehner3.jpg" server="www.kinderkultur.ch/httpdocs/" local="3535638726" remote="319783739179434988" Dst="-1" /><file name="huehner1.jpg" server="www.kinderkultur.ch/httpdocs/" local="3535638726" remote="319783739179434988" Dst="-1" /><file name="huehner6.jpg" server="www.kinderkultur.ch/httpdocs/" local="3535638726" remote="319783739179434988" Dst="-1" /><file name="huehner5.jpg" server="www.kinderkultur.ch/httpdocs/" local="3535638726" remote="319783739179434988" Dst="-1" /><file name="huehner4.jpg" server="www.kinderkultur.ch/httpdocs/" local="3535638726" remote="319783739179434988" Dst="-1" /><file name="huehner7.jpg" server="www.kinderkultur.ch/httpdocs/" local="3535638727" remote="319783739179434988" Dst="-1" /><file name="achdiesehuehnenplakat.jpg" server="www.kinderkultur.ch/httpdocs/2/" local="3535638725" remote="319783739179735708" Dst="-1" /><file name="huehner1.jpg" server="www.kinderkultur.ch/httpdocs/2/" local="3535638726" remote="319783739179735708" Dst="-1" /><file name="huehner2.jpg" server="www.kinderkultur.ch/httpdocs/2/" local="3535638726" remote="319783739179735708" Dst="-1" /><file name="huehner3.jpg" server="www.kinderkultur.ch/httpdocs/2/" local="3535638726" remote="319783739179735708" Dst="-1" /><file name="huehner4.jpg" server="www.kinderkultur.ch/httpdocs/2/" local="3535638726" remote="319783739179735708" Dst="-1" /><file name="huehner5.jpg" server="www.kinderkultur.ch/httpdocs/2/" local="3535638726" remote="319783739179735708" Dst="-1" /><file name="huehner6.jpg" server="www.kinderkultur.ch/httpdocs/2/" local="3535638726" remote="319783739179735708" Dst="-1" /><file name="huehner7.jpg" server="www.kinderkultur.ch/httpdocs/2/" local="3535638727" remote="319783739179735708" Dst="-1" /><file name="Plakat-Huehner-neu.jpg" server="www.kinderkultur.ch/httpdocs/2/" local="3535638725" remote="319783739179735708" Dst="-1" /></dwsync>